simuwave/__init__.py
simuwave-0.0.1.dist-info/LICENSE
simuwave-0.0.1.dist-info/METADATA
simuwave-0.0.1.dist-info/WHEEL
simuwave-0.0.1.dist-info/top_level.txt
simuwave-0.0.1.dist-info/RECORD
