Metadata-Version: 2.1
Name: simuwave
Version: 0.0.1
Summary: rf/microwave network simulation tool
Author-email: Rick Lyon <rlyon14@gmail.com>
License: MIT License
Project-URL: repository, https://github.com/ricklyon/simuwave
Keywords: rf,microwave,network,noise,modeling
Classifier: License :: OSI Approved :: MIT License
Classifier: Programming Language :: Python
Classifier: Programming Language :: Python :: 3
Requires-Python: >=3.7
License-File: LICENSE
Requires-Dist: numpy
Requires-Dist: matplotlib
Provides-Extra: dev
Requires-Dist: black ; extra == 'dev'
Requires-Dist: flake8 ; extra == 'dev'
Requires-Dist: pytest ; extra == 'dev'
